setup.cfg
setup.py
function_speed/__init__.py
function_speed/function_speed.py
function_speed.egg-info/PKG-INFO
function_speed.egg-info/SOURCES.txt
function_speed.egg-info/dependency_links.txt
function_speed.egg-info/not-zip-safe
function_speed.egg-info/top_level.txt