Metadata-Version: 2.1
Name: function-speed
Version: 0.0.0
Summary: This litle library is measures speed of functions
Author-email: vyamak@hotmail.com
